delma/__init__.py
delma/check_eml.py
delma/check_eml_xml.py
delma/check_metadata.py
delma/common_dictionaries.py
delma/create_md.py
delma/display_as_dataframe.py
delma/metadata_template.md
delma/recursive_md_function.py
delma/version.py
delma/write_eml.py
delma/write_eml_xml.py
paperbark/__init__.py
paperbark/build_subelement.py
paperbark/check_eml_xml.py
paperbark/common_dictionaries.py
paperbark/create_md.py
paperbark/create_metadata_file.py
paperbark/display_as_dataframe.py
paperbark/metadata_template.md
paperbark/recursive_md_function.py
paperbark/use_eml_xml.py
paperbark/version.py
delma_python-0.1.5.dist-info/METADATA
delma_python-0.1.5.dist-info/WHEEL
delma_python-0.1.5.dist-info/top_level.txt
delma_python-0.1.5.dist-info/RECORD
